[	 
	{
		 "npcId": 70,
		 "attack": 25,
		 "strength": 25,
		 "defence": 30,
		 "ranged": 0,
		 "magic": 0,	 
		 "stabAttack": 0,
		 "slashAttack": 0,
		 "crushAttack": 0,
		 "magicAttack": 0,
		 "rangedAttack": 0,		 
		 "stabDefence": 15,
		 "slashDefence": 15,
		 "crushDefence": 15,
		 "magicDefence": 15,
		 "rangedDefence": 20, 
		 "rangedStrength": 0,
		 "magicStrength": 0
	 },
{
		 "npcId": 2098,
		 "attack": 36,
		 "strength": 38,
		 "defence": 26,
		 "ranged": 1,
		 "magic": 1,	 
		 "stabAttack": 18,
		 "slashAttack": 18,
		 "crushAttack": 18,
		 "magicAttack": 0,
		 "rangedAttack": 0,		 
		 "stabDefence": 0,
		 "slashDefence": 0,
		 "crushDefence": 0,
		 "magicDefence": 0,
		 "rangedDefence": 0, 
		 "rangedStrength": 0,
		 "magicStrength": 0
	 },
{
		 "npcId": 3407,
		 "attack": 180,
		 "strength": 250,
		 "defence": 600,
		 "ranged":120,
		 "magic": 300,	 
		 "stabAttack": 18,
		 "slashAttack": 18,
		 "crushAttack": 280,
		 "magicAttack": 250,
		 "rangedAttack": 100,		 
		 "stabDefence": 400,
		 "slashDefence": 450,
		 "crushDefence": 200,
		 "magicDefence": 150,
		 "rangedDefence": 500, 
		 "rangedStrength": 100,
		 "magicStrength": 250
	 },
	 {
		 "npcId": 8615,
		 "attack": 100,
		 "strength": 100,
		 "defence": 100,
		 "ranged": 260,
		 "magic": 260,	 
		 "stabAttack": 0,
		 "slashAttack": 0,
		 "crushAttack": 0,
		 "magicAttack": 45,
		 "rangedAttack": 45,		 
		 "stabDefence": 75,
		 "slashDefence": 150,
		 "crushDefence": 150,
		 "magicDefence": 150,
		 "rangedDefence": 45, 
		 "rangedStrength": 20,
		 "magicStrength": 20
	 },
	 {
		 "npcId": 8616,
		 "attack": 100,
		 "strength": 100,
		 "defence": 100,
		 "ranged": 260,
		 "magic": 260,	 
		 "stabAttack": 0,
		 "slashAttack": 0,
		 "crushAttack": 0,
		 "magicAttack": 45,
		 "rangedAttack": 45,		 
		 "stabDefence": 75,
		 "slashDefence": 150,
		 "crushDefence": 150,
		 "magicDefence": 150,
		 "rangedDefence": 45, 
		 "rangedStrength": 20,
		 "magicStrength": 20
	 },
	 {
		 "npcId": 8617,
		 "attack": 100,
		 "strength": 100,
		 "defence": 100,
		 "ranged": 260,
		 "magic": 260,	 
		 "stabAttack": 0,
		 "slashAttack": 0,
		 "crushAttack": 0,
		 "magicAttack": 45,
		 "rangedAttack": 45,		 
		 "stabDefence": 75,
		 "slashDefence": 150,
		 "crushDefence": 150,
		 "magicDefence": 150,
		 "rangedDefence": 45, 
		 "rangedStrength": 20,
		 "magicStrength": 20
	 },
	 {
		 "npcId": 8618,
		 "attack": 100,
		 "strength": 100,
		 "defence": 100,
		 "ranged": 260,
		 "magic": 260,	 
		 "stabAttack": 0,
		 "slashAttack": 0,
		 "crushAttack": 0,
		 "magicAttack": 45,
		 "rangedAttack": 45,		 
		 "stabDefence": 75,
		 "slashDefence": 150,
		 "crushDefence": 150,
		 "magicDefence": 150,
		 "rangedDefence": 45, 
		 "rangedStrength": 20,
		 "magicStrength": 20
	 },
	 {
		 "npcId": 8619,
		 "attack": 100,
		 "strength": 100,
		 "defence": 100,
		 "ranged": 260,
		 "magic": 260,	 
		 "stabAttack": 0,
		 "slashAttack": 0,
		 "crushAttack": 0,
		 "magicAttack": 45,
		 "rangedAttack": 45,		 
		 "stabDefence": 75,
		 "slashDefence": 150,
		 "crushDefence": 150,
		 "magicDefence": 150,
		 "rangedDefence": 45, 
		 "rangedStrength": 20,
		 "magicStrength": 20
	 },
	 {
		 "npcId": 8620,
		 "attack": 100,
		 "strength": 100,
		 "defence": 100,
		 "ranged": 260,
		 "magic": 260,	 
		 "stabAttack": 0,
		 "slashAttack": 0,
		 "crushAttack": 0,
		 "magicAttack": 45,
		 "rangedAttack": 45,		 
		 "stabDefence": 75,
		 "slashDefence": 150,
		 "crushDefence": 150,
		 "magicDefence": 150,
		 "rangedDefence": 45, 
		 "rangedStrength": 20,
		 "magicStrength": 20
	 },
	 {
		 "npcId": 8621,
		 "attack": 100,
		 "strength": 100,
		 "defence": 100,
		 "ranged": 260,
		 "magic": 260,	 
		 "stabAttack": 0,
		 "slashAttack": 0,
		 "crushAttack": 0,
		 "magicAttack": 45,
		 "rangedAttack": 45,		 
		 "stabDefence": 75,
		 "slashDefence": 150,
		 "crushDefence": 150,
		 "magicDefence": 150,
		 "rangedDefence": 45, 
		 "rangedStrength": 20,
		 "magicStrength": 20
	 },
	 {
		 "npcId": 8622,
		 "attack": 100,
		 "strength": 100,
		 "defence": 100,
		 "ranged": 260,
		 "magic": 260,	 
		 "stabAttack": 0,
		 "slashAttack": 0,
		 "crushAttack": 0,
		 "magicAttack": 45,
		 "rangedAttack": 45,		 
		 "stabDefence": 75,
		 "slashDefence": 150,
		 "crushDefence": 150,
		 "magicDefence": 150,
		 "rangedDefence": 45, 
		 "rangedStrength": 20,
		 "magicStrength": 20
	 },
	 {
		 "npcId": 5462,
		 "attack": 300,
		 "strength": 300,
		 "defence": 300,
		 "ranged": 300,
		 "magic": 0,	 
		 "stabAttack": 0,
		 "slashAttack": 0,
		 "crushAttack": 0,
		 "magicAttack": 0,
		 "rangedAttack": 0,		 
		 "stabDefence": 200,
		 "slashDefence": 200,
		 "crushDefence": 200,
		 "magicDefence": 350,
		 "rangedDefence": 100, 
		 "rangedStrength": 60,
		 "magicStrength": 0
	 },
	 {
		 "npcId": 7795,
		 "attack": 150,
		 "strength": 150,
		 "defence": 150,
		 "ranged": 90,
		 "magic": 90,	 
		 "stabAttack": 0,
		 "slashAttack": 0,
		 "crushAttack": 0,
		 "magicAttack": 0,
		 "rangedAttack": 0,		 
		 "stabDefence": 70,
		 "slashDefence": 70,
		 "crushDefence": 70,
		 "magicDefence": 170,
		 "rangedDefence": 120, 
		 "rangedStrength": 0,
		 "magicStrength": 0
	 },
	 {
		 "npcId": 7794,
		 "attack": 125,
		 "strength": 80,
		 "defence": 90,
		 "ranged": 125,
		 "magic": 125,	 
		 "stabAttack": 0,
		 "slashAttack": 0,
		 "crushAttack": 0,
		 "magicAttack": 0,
		 "rangedAttack": 0,		 
		 "stabDefence": 70,
		 "slashDefence": 70,
		 "crushDefence": 70,
		 "magicDefence": 140,
		 "rangedDefence": 120, 
		 "rangedStrength": 0,
		 "magicStrength": 0
	 },
	 {
		 "npcId": 7793,
		 "attack": 120,
		 "strength": 110,
		 "defence": 90,
		 "ranged": 90,
		 "magic": 90,	 
		 "stabAttack": 0,
		 "slashAttack": 0,
		 "crushAttack": 0,
		 "magicAttack": 0,
		 "rangedAttack": 0,		 
		 "stabDefence": 70,
		 "slashDefence": 70,
		 "crushDefence": 70,
		 "magicDefence": 140,
		 "rangedDefence": 120, 
		 "rangedStrength": 0,
		 "magicStrength": 0
	 },
	 {
		 "npcId": 7792,
		 "attack": 125,
		 "strength": 120,
		 "defence": 90,
		 "ranged": 90,
		 "magic": 90,	 
		 "stabAttack": 0,
		 "slashAttack": 0,
		 "crushAttack": 0,
		 "magicAttack": 0,
		 "rangedAttack": 0,		 
		 "stabDefence": 70,
		 "slashDefence": 70,
		 "crushDefence": 70,
		 "magicDefence": 140,
		 "rangedDefence": 120, 
		 "rangedStrength": 0,
		 "magicStrength": 0
	 },
	 {
		 "npcId": 2215,
		 "attack": 280,
		 "strength": 350,
		 "defence": 250,
		 "ranged": 80,
		 "magic": 350,	 
		 "stabAttack": 0,
		 "slashAttack": 0,
		 "crushAttack": 0,
		 "magicAttack": 0,
		 "rangedAttack": 100,		 
		 "stabDefence": 90,
		 "slashDefence": 90,
		 "crushDefence": 90,
		 "magicDefence": 298,
		 "rangedDefence": 90, 
		 "rangedStrength": 40,
		 "magicStrength": 0
	 },
	 {
		 "npcId": 8360,
		 "attack": 350,
		 "strength": 350,
		 "defence": 200,
		 "ranged": 350,
		 "magic": 350,	 
		 "stabAttack": 0,
		 "slashAttack": 0,
		 "crushAttack": 0,
		 "magicAttack": 300,
		 "rangedAttack": 0,		 
		 "stabDefence": 0,
		 "slashDefence": 0,
		 "crushDefence": 0,
		 "magicDefence": 0,
		 "rangedDefence": 0, 
		 "rangedStrength": 0,
		 "magicStrength": 0
	 },
	 {
		 "npcId": 8361,
		 "attack": 350,
		 "strength": 350,
		 "defence": 200,
		 "ranged": 350,
		 "magic": 350,	 
		 "stabAttack": 0,
		 "slashAttack": 0,
		 "crushAttack": 0,
		 "magicAttack": 300,
		 "rangedAttack": 0,		 
		 "stabDefence": 0,
		 "slashDefence": 0,
		 "crushDefence": 0,
		 "magicDefence": 0,
		 "rangedDefence": 0, 
		 "rangedStrength": 0,
		 "magicStrength": 0
	 },
	 {
		 "npcId": 8362,
		 "attack": 350,
		 "strength": 350,
		 "defence": 200,
		 "ranged": 350,
		 "magic": 350,	 
		 "stabAttack": 0,
		 "slashAttack": 0,
		 "crushAttack": 0,
		 "magicAttack": 300,
		 "rangedAttack": 0,		 
		 "stabDefence": 0,
		 "slashDefence": 0,
		 "crushDefence": 0,
		 "magicDefence": 0,
		 "rangedDefence": 0, 
		 "rangedStrength": 0,
		 "magicStrength": 0
	 },
	 {
		 "npcId": 8363,
		 "attack": 350,
		 "strength": 350,
		 "defence": 200,
		 "ranged": 350,
		 "magic": 350,	 
		 "stabAttack": 0,
		 "slashAttack": 0,
		 "crushAttack": 0,
		 "magicAttack": 300,
		 "rangedAttack": 0,		 
		 "stabDefence": 0,
		 "slashDefence": 0,
		 "crushDefence": 0,
		 "magicDefence": 0,
		 "rangedDefence": 0, 
		 "rangedStrength": 0,
		 "magicStrength": 0
	 },
	 {
		 "npcId": 8364,
		 "attack": 350,
		 "strength": 350,
		 "defence": 200,
		 "ranged": 350,
		 "magic": 350,	 
		 "stabAttack": 0,
		 "slashAttack": 0,
		 "crushAttack": 0,
		 "magicAttack": 300,
		 "rangedAttack": 0,		 
		 "stabDefence": 0,
		 "slashDefence": 0,
		 "crushDefence": 0,
		 "magicDefence": 0,
		 "rangedDefence": 0, 
		 "rangedStrength": 0,
		 "magicStrength": 0
	 },
	 {
		 "npcId": 8365,
		 "attack": 350,
		 "strength": 350,
		 "defence": 200,
		 "ranged": 350,
		 "magic": 350,	 
		 "stabAttack": 0,
		 "slashAttack": 0,
		 "crushAttack": 0,
		 "magicAttack": 300,
		 "rangedAttack": 0,		 
		 "stabDefence": 0,
		 "slashDefence": 0,
		 "crushDefence": 0,
		 "magicDefence": 0,
		 "rangedDefence": 0, 
		 "rangedStrength": 0,
		 "magicStrength": 0
	 }
]